taskmap/__init__.py
taskmap/logparse.py
taskmap/taskmap.py
taskmap/taskmap_test.py
taskmap/tgraph.py
taskmap-0.0.6.dist-info/DESCRIPTION.rst
taskmap-0.0.6.dist-info/METADATA
taskmap-0.0.6.dist-info/RECORD
taskmap-0.0.6.dist-info/WHEEL
taskmap-0.0.6.dist-info/metadata.json
taskmap-0.0.6.dist-info/top_level.txt
