Metadata-Version: 2.0
Name: taskmap
Version: 0.0.6
Summary: Dependency graph with parallel asyncronous task runner
Home-page: https://github.com/n-s-f/taskmap
Author: UNKNOWN
Author-email: UNKNOWN
License: UNKNOWN
Platform: UNKNOWN
Requires-Dist: multiprocess
Requires-Dist: multiprocessing-logging
